waveview/tests/data/smoke.vhd
-- Source for tests/data/smoke.vcd. Regenerated only when intentionally
-- bumping the snapshot; see waveview/README.md.
library ieee;
use ieee.std_logic_1164.all;
use ieee.numeric_std.all;

entity smoke is
end entity;

architecture sim of smoke is
    signal clk     : std_logic := '0';
    signal counter : unsigned(7 downto 0) := (others => '0');
    signal done    : boolean := false;
begin
    clk <= not clk after 5 ns when not done else '0';

    process(clk)
    begin
        if rising_edge(clk) then
            counter <= counter + 1;
            if counter = x"0F" then
                done <= true;
            end if;
        end if;
    end process;
end architecture;

waveview/tests/data/smoke.vcd
$date
  Sat Apr 25 11:07:38 2026
$end
$version
  GHDL v0
$end
$timescale
  1 fs
$end
$scope module standard $end
$upscope $end
$scope module std_logic_1164 $end
$upscope $end
$scope module numeric_std $end
$upscope $end
$scope module smoke $end
$var reg 1 ! clk $end
$var reg 8 " counter[7:0] $end
$var reg 1 # done $end
$upscope $end
$enddefinitions $end
#0
0!
b00000000 "
0#
#5000000
1!
b00000001 "
#10000000
0!
#15000000
1!
b00000010 "
#20000000
0!
#25000000
1!
b00000011 "
#30000000
0!
#35000000
1!
b00000100 "
#40000000
0!
#45000000
1!
b00000101 "
#50000000
0!
#55000000
1!
b00000110 "
#60000000
0!
#65000000
1!
b00000111 "
#70000000
0!
#75000000
1!
b00001000 "
#80000000
0!
#85000000
1!
b00001001 "
#90000000
0!
#95000000
1!
b00001010 "
#100000000
0!
#105000000
1!
b00001011 "
#110000000
0!
#115000000
1!
b00001100 "
#120000000
0!
#125000000
1!
b00001101 "
#130000000
0!
#135000000
1!
b00001110 "
#140000000
0!
#145000000
1!
b00001111 "
#150000000
0!
#155000000
0!
b00010000 "
1#
